pypebbleapi/__init__.py
pypebbleapi/schemas.py
pypebbleapi/timeline.py
pypebbleapi-1.0.0.dist-info/top_level.txt
pypebbleapi-1.0.0.dist-info/METADATA
pypebbleapi-1.0.0.dist-info/DESCRIPTION.rst
pypebbleapi-1.0.0.dist-info/metadata.json
pypebbleapi-1.0.0.dist-info/WHEEL
pypebbleapi-1.0.0.dist-info/RECORD
